illusionanime/__init__.py
illusionanime/main.py
illusionanime-0.0.1.dist-info/METADATA
illusionanime-0.0.1.dist-info/WHEEL
illusionanime-0.0.1.dist-info/top_level.txt
illusionanime-0.0.1.dist-info/RECORD
